[
  {
    "name": "HP DesignJet T230 24-in Printer",
    "sku": "5HB07D#AC4",
    "short_description": "HP DesignJet T230 24-in Printer",
    "description": "Concentre-se no projeto, não na sua plotter. Essa impressora oferece uma facilidade incrível de uso com as Soluções de Impressão HP Click.[2] Foi desenvolvida de forma responsável para ajudar você a economizar energia[4] e a reduzir o uso de plásticos.[7] Além disso, é compacta e adaptável, para se adaptar à sua maneira de trabalhar. INTUITIVA – Impressão simples e fácil Simplifique a impressão com as novas Soluções de Impressão HP Click; economize tempo com a pré-visualização real da impressão.[2] Com um acessório, imprima projetos A4/A a A1/D de vários tamanhos sem trocar a fonte de mídia manualmente.[3] Imprima seus trabalhos e gerencie sua plotter, praticamente de qualquer lugar, a qualquer hora com o aplicativo HP.[4] DESENVOLVIDA COM RESPONSABILIDADE — Reduza o consumo de energia e o uso de plástico Economize 65% de energia[5] com o agendamento automático para ligar/desligar a impressora e desfrute de rotinas de manutenção de tinta eficientes.[6] Minimize o desperdício de plástico em mais de 70% com uma nova embalagem de fibra moldada e remoção da maioria dos sacos plásticos.[7] Fabricada com pelo menos 40% de plástico reciclado[8] e a primeira impressora de grande formato da HP  a conter metal reciclado.[9] Certificada pela UL ECOLOGO®.[10] Registrada no EPEAT Gold e conquistou o EPEAT Climate+.[11] OTIMIZADA – Adapta-se ao seu jeito de trabalhar Economize espaço com as menores plotters do mundo[1] desenvolvidas para se adaptar ao seu escritório. Evite esperar pela impressora, com impressão em apenas 35 segundos por plotagem A1/D.[12] Proteja sua impressora contra ameaças cibernéticas com o HP Wolf Essential Security. Obtenha de resultados de alta qualidade: as tintas HP Bright Office oferecem melhor precisão de linha[13] e até 34% mais gama de cores.[14] ",
    "price": "2864.78",
    "regular_price": "2864.78",
    "stock_quantity": "10",
    "attributes": [
      {
        "id": 16,
        "options": "Impressora HP DesignJet T230 24 polegadas, cabeça de impressão, cartuchos de tinta introdutórios, eixo, guia de referência rápida, pôster de configuração, cabo de alimentação",
        "visible": true
      },
      {
        "id": 21,
        "options": "Tensão de entrada (escala automática): 100-240V (±10%), 50/60Hz (±3Hz), 1200mA máx",
        "visible": true
      },
      {
        "id": 22,
        "options": "Garantia limitada de 1 ano para o hardware",
        "visible": true
      },
      {
        "id": 25,
        "options": "512 MB",
        "visible": true
      },
      {
        "id": 39,
        "options": "Nenhum",
        "visible": true
      },
      {
        "id": 42,
        "options": "Touchscreen",
        "visible": true
      },
      {
        "id": 44,
        "options": "Apple AirPrint™; Ethernet networking; USB; Wireless (Wi-Fi®); Wireless direct printing",
        "visible": true
      },
      {
        "id": 82,
        "options": "Baseado em tinta (C, M, Y); baseado em pigmentos (K)",
        "visible": true
      },
      {
        "id": 827,
        "options": "Ciano, magenta, amarelo, preto",
        "visible": true
      },
      {
        "id": 828,
        "options": "1 (ciano, magenta, amarelo, preto)",
        "visible": true
      },
      {
        "id": 829,
        "options": "Gigabit Ethernet (1000Base-T), USB 2.0 de alta velocidade, Wi-Fi 802.11a/b/g/n, Wi-Fi Direct",
        "visible": true
      },
      {
        "id": 830,
        "options": "5 a 40 ºC",
        "visible": true
      },
      {
        "id": 831,
        "options": "-25 a 55ºC",
        "visible": true
      },
      {
        "id": 832,
        "options": "35 s/página em A1, 68 impressões em A1 por hora[1]",
        "visible": true
      },
      {
        "id": 833,
        "options": "HP Thermal Inkjet",
        "visible": true
      },
      {
        "id": 834,
        "options": "Imprimir",
        "visible": true
      },
      {
        "id": 835,
        "options": "Até 2400 x 1200 dpi otimizados",
        "visible": true
      },
      {
        "id": 836,
        "options": "JPEG, URF",
        "visible": true
      },
      {
        "id": 837,
        "options": "5 x 5 x 5 x 17 mm (alimentação manual); 5 x 5 x 5 x 5 mm (bandeja de entrada)",
        "visible": true
      },
      {
        "id": 838,
        "options": "±0,1%[3]",
        "visible": true
      },
      {
        "id": 839,
        "options": "",
        "visible": true
      },
      {
        "id": 840,
        "options": "A4, A3, A2, A1",
        "visible": true
      },
      {
        "id": 841,
        "options": "210 x 279 a 610 x 1897 mm",
        "visible": true
      },
      {
        "id": 842,
        "options": "Papéis comuns e revestidos (comum, revestido, revestido de gramatura alta, reciclado, simples, branco brilhante), papéis técnicos (papel vegetal, vellum), filme (transparente, fosco), papel fotográfico (acetinado, brilhante, semibrilhante, premium, polipropileno), autoadesivo (adesivo, propileno)",
        "visible": true
      },
      {
        "id": 843,
        "options": "100 mm",
        "visible": true
      },
      {
        "id": 844,
        "options": "Até 11,8 milímetros",
        "visible": true
      }
    ],
    "meta_data": [
      {
        "key": "_external_image_url",
        "value": "https://hp.widen.net/content/vntlt34epb/png/vntlt34epb.png"
      },
      {
        "key": "_external_gallery_images",
        "value": [
          "https://hp.widen.net/content/ndqpsglppn/png/ndqpsglppn.png",
          "https://ssl-product-images.www8-hp.com/digmedialib/prodimg/lowres/c06903745.png",
          "https://hp.widen.net/content/hkfhrb1vch/png/hkfhrb1vch.png",
          "https://ssl-product-images.www8-hp.com/digmedialib/prodimg/lowres/c06903855.png"
        ]
      }
    ],
    "dimensions": {
      "length": "115.5",
      "width": "57.5",
      "height": "40.5"
    },
    "weight": "27",
    "categories": [
      {
        "id": 24
      }
    ],
    "shipping_class": "importado",
    "manage_stock": true
  },
  {
    "name": "HP DesignJet Z6 24-in PS Printer:NA/LA",
    "sku": "T8W15A#B1K",
    "short_description": "HP DesignJet Z6 24-in PS Printer:NA/LA",
    "description": "Leia os detalhes com mais clareza e veja cores de alto contraste com as novas cabeças de impressão HP de alta definição. O HP Pixel Control permite gradientes suaves e o aparador vertical integrado agiliza o acabamento.[3] Manuseie arquivos complexos e proteja suas impressoras/dados. PRECISA: distingue claramente os detalhes sutis Leia os detalhes com mais clareza e veja cores de alto contraste com as novas cabeças de impressão HP de alta definição. Não há necessidade de tintas claras com a tecnologia de gota dupla da HP. Obtenha gradientes suaves, mesmo para combinações de cores desafiadoras, com o HP Pixel Control. RÁPIDA: trabalhe sem atrasos Manipule até mesmo os arquivos mais complexos com uma poderosa arquitetura de processamento e o Adobe PDF Print Engine.[2] Corte mapas em tamanhos diferentes em menos etapas usando a primeira impressora com um aparador vertical integrado.[3] Imprima até 20% mais rápido[4] com 2400 cabeças de impressão HP de alta definição por polegada. Gaste menos tempo com alterações e ajustes de mídia com suporte a rolo duplo e troca automática de rolo.[3] SEGURO – proteja seu trabalho e suas informações Proteja impressoras/dados contra acesso não autorizado com a Inicialização segura HP, lista de permissões e disco rígido criptografado. Proteja documentos, preserve a confidencialidade com soluções de autenticação como impressão PIN, leitores de cartão.[5] Proteja suas impressoras com o HP JetAdvantage Security Manager; gerencie sua frota remotamente com a HP Web Jetadmin. ",
    "price": "21181.64",
    "regular_price": "21181.64",
    "stock_quantity": "10",
    "attributes": [
      {
        "id": 16,
        "options": "Impressora HP DesignJet Z6 PostScript, cabeças de impressão, cartuchos de tinta iniciais, suporte para impressora e bandeja de mídia, eixo, guia referência rápida, pôster de instalação, cabo de alimentação",
        "visible": true
      },
      {
        "id": 21,
        "options": "Tensão de entrada (escala automática): 100-240 V (±10%), 50/60 Hz (±3 Hz), 2 A máx",
        "visible": true
      },
      {
        "id": 22,
        "options": "Garantia limitada de 1 ano para o hardware",
        "visible": true
      },
      {
        "id": 25,
        "options": "128 GB (virtual)[8]",
        "visible": true
      },
      {
        "id": 39,
        "options": "500 GB com autocriptografia",
        "visible": true
      },
      {
        "id": 42,
        "options": "Não",
        "visible": true
      },
      {
        "id": 44,
        "options": "",
        "visible": true
      },
      {
        "id": 82,
        "options": "Com pigmentos",
        "visible": true
      },
      {
        "id": 827,
        "options": "Ciano, magenta, amarelo, preto fosco, preto fotográfico, vermelho cromático",
        "visible": true
      },
      {
        "id": 828,
        "options": "3 cabeças de impressão universais (válidas para todas as cores)",
        "visible": true
      },
      {
        "id": 829,
        "options": "Gigabit Ethernet (1000Base-T) (802.3, 802.3u, 802.3ab); Interface certificada USB 2.0 de alta velocidade para impressão direta de unidade flash USB",
        "visible": true
      },
      {
        "id": 830,
        "options": "5 a 40 ºC",
        "visible": true
      },
      {
        "id": 831,
        "options": "-25 a 55ºC",
        "visible": true
      },
      {
        "id": 832,
        "options": "Rápido: 66,9 m²/h em mídia comum; Normal: 15,2 m²/h em mídia revestida; Melhor: 7,9 m²/h em mídia brilhante[1]",
        "visible": true
      },
      {
        "id": 833,
        "options": "HP Thermal Inkjet",
        "visible": true
      },
      {
        "id": 834,
        "options": "Imprimir",
        "visible": true
      },
      {
        "id": 835,
        "options": "Até 2400 x 1200 dpi otimizados",
        "visible": true
      },
      {
        "id": 836,
        "options": "Adobe PostScript 3, Adobe PDF 1.7, TIFF, JPEG, CALS G4, HP-GL/2, HP-RTL",
        "visible": true
      },
      {
        "id": 837,
        "options": "5 x 17 x 5 x 5 mm",
        "visible": true
      },
      {
        "id": 838,
        "options": "±0,1%[5]",
        "visible": true
      },
      {
        "id": 839,
        "options": "<1 dE2000 em menos de 5 minutos[7]",
        "visible": true
      },
      {
        "id": 840,
        "options": "A4, A3, A2, A1",
        "visible": true
      },
      {
        "id": 841,
        "options": "210 x 279 a 610 x 1676 mm",
        "visible": true
      },
      {
        "id": 842,
        "options": "Papel fotográfico, material de impressão artística, autoadesivo, banner e sinalização, comum e revestido, com retroiluminação",
        "visible": true
      },
      {
        "id": 843,
        "options": "135 mm",
        "visible": true
      },
      {
        "id": 844,
        "options": "Até 274,05 mícrons",
        "visible": true
      }
    ],
    "meta_data": [
      {
        "key": "_external_image_url",
        "value": "https://ssl-product-images.www8-hp.com/digmedialib/prodimg/lowres/c06015522.png"
      },
      {
        "key": "_external_gallery_images",
        "value": [
          "https://hp.widen.net/content/f4v6zgxaj5/png/f4v6zgxaj5.png",
          "https://hp.widen.net/content/fxiepsebxi/png/fxiepsebxi.png",
          "https://hp.widen.net/content/d0ewscyg8o/png/d0ewscyg8o.png",
          "https://hp.widen.net/content/fajuwuv1ab/png/fajuwuv1ab.png"
        ]
      }
    ],
    "dimensions": {
      "length": "144.0",
      "width": "76.6",
      "height": "71.8"
    },
    "weight": "97",
    "categories": [
      {
        "id": 24
      }
    ],
    "shipping_class": "local",
    "manage_stock": true
  },
  {
    "name": "HP DesignJet T850 36-in Printer:NA/LA",
    "sku": "2Y9H0A#AC4",
    "short_description": "HP DesignJet T850 36-in Printer:NA/LA",
    "description": "Maximize a agilidade da sua equipe com a experiência A3-A1 mais fácil do mundo.[1] Simplifique a impressão em vários tamanhos com a bandeja de entrada integrada. Simplifique os fluxos de trabalho de impressão com o HP Click. E atenda às necessidades corporativas e ambientais com essa impressora plotter compacta. MAIS FÁCIL[1]: impressão em vários tamanhos com um clique Imprima todos os tamanhos: além de imprimir trabalhos A3 usando a bandeja de entrada integrada, não é necessário alterar manualmente do rolo para as folhas. Obtenha impressões de renderizações e arquivos CAD de alta qualidade e em vários tamanhos com as tintas HP Flex Tech. Evite distrações com menos intervenções de tinta graças aos cartuchos de 130/300 ml. CONECTADO: trabalhe com segurança de praticamente qualquer lugar Simplifique a impressão com as novas Soluções de Impressão HP Click - Economize tempo com a pré-visualização real da impressão.[3] Proteja sua impressora e seus dados contra ameaças cibernéticas sem precisar fazer nenhum esforço, graças ao HP Wolf Pro Security. VÁ ALÉM: atenda às necessidades corporativas e ambientais Metas ambientais avançadas: a impressora é fabricada com pelo menos 35% de plástico reciclado[4] e suprimentos recicláveis[5]. Invista em uma impressora plotter robusta e compacta, que foi desenvolvida para durabilidade. Reduza o consumo de energia e de tinta: com a programação automática de ativação/desativação do uso da impressora, você aproveita os benefícios das rotinas eficientes de manutenção de tinta. ",
    "price": "13776.76",
    "regular_price": "13776.76",
    "stock_quantity": "10",
    "attributes": [
      {
        "id": 16,
        "options": "Impressora HP DesignJet T850, cabeça de impressão, cartuchos de tinta introdutórios, pedestal para impressora, eixo, guia, folheto de garantia, cabo de alimentação",
        "visible": true
      },
      {
        "id": 21,
        "options": "Tensão de entrada (escala automática): 100-240V (±10%), 50/60Hz (±3Hz), 1,2A máx",
        "visible": true
      },
      {
        "id": 22,
        "options": "Garantia limitada de um ano para o hardware. A garantia e as opções de assistência variam conforme o produto, o país e a legislação local.",
        "visible": true
      },
      {
        "id": 25,
        "options": "1 GB ",
        "visible": true
      },
      {
        "id": 39,
        "options": "Nenhum",
        "visible": true
      },
      {
        "id": 42,
        "options": "Touchscreen",
        "visible": true
      },
      {
        "id": 44,
        "options": "Apple AirPrint™; Ethernet networking; Wireless (Wi-Fi®); Wireless direct printing",
        "visible": true
      },
      {
        "id": 82,
        "options": "À base de pigmentos (C, M, Y, mK)",
        "visible": true
      },
      {
        "id": 827,
        "options": "Ciano, magenta, amarelo, preto fosco",
        "visible": true
      },
      {
        "id": 828,
        "options": "1 (C, M, Y, mK)",
        "visible": true
      },
      {
        "id": 829,
        "options": "Gigabit Ethernet (1000Base-T), Wi-Fi 802.11b/g/n",
        "visible": true
      },
      {
        "id": 830,
        "options": "5 a 40° C",
        "visible": true
      },
      {
        "id": 831,
        "options": "-25° a 55° C",
        "visible": true
      },
      {
        "id": 832,
        "options": "25 seg./página em A1, 90 impressões em A1 por hora[1]",
        "visible": true
      },
      {
        "id": 833,
        "options": "HP Thermal Inkjet",
        "visible": true
      },
      {
        "id": 834,
        "options": "Imprimir",
        "visible": true
      },
      {
        "id": 835,
        "options": "Até 2400 x 1200 dpi otimizados",
        "visible": true
      },
      {
        "id": 836,
        "options": "TIFF, JPEG, URF, HP-GL/2, HP-RTL, CALS G4",
        "visible": true
      },
      {
        "id": 837,
        "options": "5 x 5 x 5 x 5 mm",
        "visible": true
      },
      {
        "id": 838,
        "options": "±0,1%[2]",
        "visible": true
      },
      {
        "id": 839,
        "options": "",
        "visible": true
      },
      {
        "id": 840,
        "options": "Bandeja de entrada: A4, A3; Alimentação manual: A4, A3, A2, A1, A0",
        "visible": true
      },
      {
        "id": 841,
        "options": "Bandeja de entrada: 210 x 279 a 305 x 457 mm; Alimentação manual: 210 x 279 a 914 x 1676 mm",
        "visible": true
      },
      {
        "id": 842,
        "options": "Papéis comuns e revestidos (comum, revestido, revestido de gramatura alta, reciclado, simples, branco brilhante), papéis técnicos (papel vegetal), película (transparente, fosco), papel fotográfico (acetinado ID, brilhante ID), autoadesivo (fosco/brilhante adesivo, brilhante polipropileno adesivo), polipropileno (fosco)",
        "visible": true
      },
      {
        "id": 843,
        "options": "100 mm",
        "visible": true
      },
      {
        "id": 844,
        "options": "Até 11,8 milímetros",
        "visible": true
      }
    ],
    "meta_data": [
      {
        "key": "_external_image_url",
        "value": "https://hp.widen.net/content/l07zdvjlz4/png/l07zdvjlz4.png"
      },
      {
        "key": "_external_gallery_images",
        "value": [
          "https://hp.widen.net/content/jiejneqkv0/png/jiejneqkv0.png",
          "https://hp.widen.net/content/rkxdooyhzf/png/rkxdooyhzf.png",
          "https://hp.widen.net/content/tri6wry7ta/png/tri6wry7ta.png",
          "https://hp.widen.net/content/7lumstrxz8/png/7lumstrxz8.png"
        ]
      }
    ],
    "dimensions": {
      "length": "157.5",
      "width": "57.0",
      "height": "65.0"
    },
    "weight": "71",
    "categories": [
      {
        "id": 24
      }
    ],
    "shipping_class": "importado",
    "manage_stock": true
  }
]